measurement_converter/__init__.py
measurement_converter/constants.py
measurement_converter/converter.py
measurement_converter/errors.py
measurement_converter/types.py
measurement_converter/utils.py
measurement_converter-1.0.1.dist-info/METADATA
measurement_converter-1.0.1.dist-info/WHEEL
measurement_converter-1.0.1.dist-info/top_level.txt
measurement_converter-1.0.1.dist-info/RECORD
