Metadata-Version: 2.1
Name: measurement_converter
Version: 1.0.1
Summary: A powerful Python library for unit conversions
Home-page: https://github.com/OrenGrinker/measurementConverter
Author: Oren Grinker
Author-email: orengr4@gmail.com
Project-URL: Bug Tracker, https://github.com/OrenGrinker/measurementConverter/issues
Classifier: Programming Language :: Python :: 3
Classifier: License :: OSI Approved :: MIT License
Classifier: Operating System :: OS Independent
Requires-Python: >=3.7
